secure_python_utils/__init__.py
secure_python_utils/logger/__init__.py
secure_python_utils/logger/simple.py
secure_python_utils/password_hasher/__init__.py
secure_python_utils/password_hasher/argon2.py
secure_python_utils/rate_limiter/__init__.py
secure_python_utils/rate_limiter/redis_limiter.py
secure_python_utils/settings/__init__.py
secure_python_utils/settings/base.py
secure_python_utils-0.1.5.dist-info/METADATA
secure_python_utils-0.1.5.dist-info/WHEEL
secure_python_utils-0.1.5.dist-info/licenses/LICENSE
secure_python_utils-0.1.5.dist-info/RECORD
